grparking/__init__.py
grparking/amanogr.py
grparking/civicsmart.py
grparking/designagr.py
grparking/flowbirdgr.py
grparking/main.py
grparking/passportgr.py
grparking/socratagr.py
grparking-0.3.9.dist-info/LICENSE
grparking-0.3.9.dist-info/METADATA
grparking-0.3.9.dist-info/WHEEL
grparking-0.3.9.dist-info/top_level.txt
grparking-0.3.9.dist-info/RECORD
