Metadata-Version: 2.1
Name: grparking
Version: 0.3.9
Summary: Packages to export, transform, and load data from The City of Grand Rapids parking systems
Home-page: https://github.com/GRInnovation/parking_package
Author: Example Author
Author-email: digitalservices@grcity.us
License: UNKNOWN
Platform: UNKNOWN
Classifier: Programming Language :: Python :: 3
Classifier: License :: OSI Approved :: MIT License
Classifier: Operating System :: OS Independent
Requires-Python: >=3.6
